olang.py
olang_compiler.py
strings_essentials.py
O_lang-1.0.5.dist-info/LICENSE
O_lang-1.0.5.dist-info/METADATA
O_lang-1.0.5.dist-info/WHEEL
O_lang-1.0.5.dist-info/top_level.txt
O_lang-1.0.5.dist-info/RECORD
