Metadata-Version: 2.1
Name: O-lang
Version: 1.0.5
Summary: A fun programming language with odia keywords...
Home-page: UNKNOWN
Author: Saurabh Satapathy
Author-email: saurabhsatapathy0@gmail.com
License: UNKNOWN
Platform: UNKNOWN
Classifier: Programming Language :: Python :: 3
Classifier: License :: OSI Approved :: MIT License
Classifier: Operating System :: OS Independent
Requires-Python: >=3.8.10
License-File: LICENSE
